mindscript/__init__.py
mindscript/ast.py
mindscript/backend.py
mindscript/bnf.py
mindscript/builtins.py
mindscript/cli.py
mindscript/lexer.py
mindscript/objects.py
mindscript/oracle.py
mindscript/parser.py
mindscript/printer.py
mindscript/runtime.py
mindscript/schema.py
mindscript/types.py
mindscript/lib/__init__.py
mindscript/lib/lang.ms
mindscript/lib/std.ms
mindscript/libnative/auxiliary.py
mindscript/libnative/collections.py
mindscript/libnative/file.py
mindscript/libnative/math.py
mindscript/libnative/network.py
mindscript/libnative/std.py
mindscript/libnative/string.py
mindscript/libnative/system.py
mindscript-0.4.1.dist-info/licenses/LICENSE
mindscript-0.4.1.dist-info/METADATA
mindscript-0.4.1.dist-info/WHEEL
mindscript-0.4.1.dist-info/entry_points.txt
mindscript-0.4.1.dist-info/top_level.txt
mindscript-0.4.1.dist-info/RECORD
