Metadata-Version: 2.4
Name: mindscript
Version: 0.4.1
Summary: An experimental programming language combining formal and informal computation.
Author-email: Daios AI <help@daios.ai>
License: MIT License
Project-URL: Homepage, https://daios.ai
Project-URL: Bug Reports, https://github.com/DAIOS-AI/mindscript/issues
Project-URL: Source, https://github.com/DAIOS-AI/mindscript/
Keywords: programming language,unstructed data
Classifier: Development Status :: 3 - Alpha
Classifier: Intended Audience :: Developers
Classifier: License :: OSI Approved :: MIT License
Classifier: Programming Language :: Python :: 3.10
Requires-Python: >=3.9
License-File: LICENSE
Requires-Dist: pydantic>=2.7.1
Requires-Dist: requests>=2.31
Dynamic: license-file
